[{"trends":[{"name":"#IPLFinal","url":"http:\/\/twitter.com\/search?q=%23IPLFinal","promoted_content":null,"query":"%23IPLFinal","tweet_volume":74761},{"name":"Animal Crossing","url":"http:\/\/twitter.com\/search?q=%22Animal+Crossing%22","promoted_content":null,"query":"%22Animal+Crossing%22","tweet_volume":123726},{"name":"#CSKvsKKR","url":"http:\/\/twitter.com\/search?q=%23CSKvsKKR","promoted_content":null,"query":"%23CSKvsKKR","tweet_volume":59280},{"name":"Nintendo","url":"http:\/\/twitter.com\/search?q=Nintendo","promoted_content":null,"query":"Nintendo","tweet_volume":208312},{"name":"jungkook","url":"http:\/\/twitter.com\/search?q=jungkook","promoted_content":null,"query":"jungkook","tweet_volume":1008789},{"name":"David Amess","url":"http:\/\/twitter.com\/search?q=%22David+Amess%22","promoted_content":null,"query":"%22David+Amess%22","tweet_volume":120333},{"name":"ACNH","url":"http:\/\/twitter.com\/search?q=ACNH","promoted_content":null,"query":"ACNH","tweet_volume":94300},{"name":"#IPL2021Final","url":"http:\/\/twitter.com\/search?q=%23IPL2021Final","promoted_content":null,"query":"%23IPL2021Final","tweet_volume":34150},{"name":"Ertz","url":"http:\/\/twitter.com\/search?q=Ertz","promoted_content":null,"query":"Ertz","tweet_volume":35974},{"name":"#CamilaTinyDeskConcert","url":"http:\/\/twitter.com\/search?q=%23CamilaTinyDeskConcert","promoted_content":null,"query":"%23CamilaTinyDeskConcert","tweet_volume":null},{"name":"#\u0627\u0644\u062D\u064A\u0627\u0647_\u0627\u0644\u0637\u0628\u064A\u0639\u064A\u0647","url":"http:\/\/twitter.com\/search?q=%23%D8%A7%D9%84%D8%AD%D9%8A%D8%A7%D9%87_%D8%A7%D9%84%D8%B7%D8%A8%D9%8A%D8%B9%D9%8A%D9%87","promoted_content":null,"query":"%23%D8%A7%D9%84%D8%AD%D9%8A%D8%A7%D9%87_%D8%A7%D9%84%D8%B7%D8%A8%D9%8A%D8%B9%D9%8A%D9%87","tweet_volume":43214},{"name":"Jo Cox","url":"http:\/\/twitter.com\/search?q=%22Jo+Cox%22","promoted_content":null,"query":"%22Jo+Cox%22","tweet_volume":12365},{"name":"Gill","url":"http:\/\/twitter.com\/search?q=Gill","promoted_content":null,"query":"Gill","tweet_volume":244247},{"name":"\u68EE\u30A2\u30D7\u30C7","url":"http:\/\/twitter.com\/search?q=%E6%A3%AE%E3%82%A2%E3%83%97%E3%83%87","promoted_content":null,"query":"%E6%A3%AE%E3%82%A2%E3%83%97%E3%83%87","tweet_volume":35140},{"name":"Ece Mumay","url":"http:\/\/twitter.com\/search?q=%22Ece+Mumay%22","promoted_content":null,"query":"%22Ece+Mumay%22","tweet_volume":null},{"name":"Lord Shardul","url":"http:\/\/twitter.com\/search?q=%22Lord+Shardul%22","promoted_content":null,"query":"%22Lord+Shardul%22","tweet_volume":null},{"name":"amiibo\u30AB\u30FC\u30C9","url":"http:\/\/twitter.com\/search?q=amiibo%E3%82%AB%E3%83%BC%E3%83%89","promoted_content":null,"query":"amiibo%E3%82%AB%E3%83%BC%E3%83%89","tweet_volume":12953},{"name":"N64 and Genesis","url":"http:\/\/twitter.com\/search?q=%22N64+and+Genesis%22","promoted_content":null,"query":"%22N64+and+Genesis%22","tweet_volume":null},{"name":"\u8FFD\u52A0\u30D1\u30C3\u30AF","url":"http:\/\/twitter.com\/search?q=%E8%BF%BD%E5%8A%A0%E3%83%91%E3%83%83%E3%82%AF","promoted_content":null,"query":"%E8%BF%BD%E5%8A%A0%E3%83%91%E3%83%83%E3%82%AF","tweet_volume":17478},{"name":"\u3069\u3046\u3076\u3064\u306E\u68EE","url":"http:\/\/twitter.com\/search?q=%E3%81%A9%E3%81%86%E3%81%B6%E3%81%A4%E3%81%AE%E6%A3%AE","promoted_content":null,"query":"%E3%81%A9%E3%81%86%E3%81%B6%E3%81%A4%E3%81%AE%E6%A3%AE","tweet_volume":80179},{"name":"Jos\u00E9","url":"http:\/\/twitter.com\/search?q=Jos%C3%A9","promoted_content":null,"query":"Jos%C3%A9","tweet_volume":183269},{"name":"\u6709\u6599\u30B3\u30F3\u30C6\u30F3\u30C4","url":"http:\/\/twitter.com\/search?q=%E6%9C%89%E6%96%99%E3%82%B3%E3%83%B3%E3%83%86%E3%83%B3%E3%83%84","promoted_content":null,"query":"%E6%9C%89%E6%96%99%E3%82%B3%E3%83%B3%E3%83%86%E3%83%B3%E3%83%84","tweet_volume":48046},{"name":"Femi","url":"http:\/\/twitter.com\/search?q=Femi","promoted_content":null,"query":"Femi","tweet_volume":25686},{"name":"\u30CF\u30B5\u30A6\u30A7\u30A4","url":"http:\/\/twitter.com\/search?q=%E3%83%8F%E3%82%B5%E3%82%A6%E3%82%A7%E3%82%A4","promoted_content":null,"query":"%E3%83%8F%E3%82%B5%E3%82%A6%E3%82%A7%E3%82%A4","tweet_volume":23943},{"name":"FROGGY CHAIR","url":"http:\/\/twitter.com\/search?q=%22FROGGY+CHAIR%22","promoted_content":null,"query":"%22FROGGY+CHAIR%22","tweet_volume":17595},{"name":"Jeon Bam","url":"http:\/\/twitter.com\/search?q=%22Jeon+Bam%22","promoted_content":null,"query":"%22Jeon+Bam%22","tweet_volume":100649},{"name":"N\u306E\u305F\u3081\u306B","url":"http:\/\/twitter.com\/search?q=N%E3%81%AE%E3%81%9F%E3%82%81%E3%81%AB","promoted_content":null,"query":"N%E3%81%AE%E3%81%9F%E3%82%81%E3%81%AB","tweet_volume":10318},{"name":"\u6700\u5F8C\u306E\u30A2\u30D7\u30C7","url":"http:\/\/twitter.com\/search?q=%E6%9C%80%E5%BE%8C%E3%81%AE%E3%82%A2%E3%83%97%E3%83%87","promoted_content":null,"query":"%E6%9C%80%E5%BE%8C%E3%81%AE%E3%82%A2%E3%83%97%E3%83%87","tweet_volume":11723},{"name":"Happy Home Designer","url":"http:\/\/twitter.com\/search?q=%22Happy+Home+Designer%22","promoted_content":null,"query":"%22Happy+Home+Designer%22","tweet_volume":null},{"name":"Jadeja","url":"http:\/\/twitter.com\/search?q=Jadeja","promoted_content":null,"query":"Jadeja","tweet_volume":14402},{"name":"Expansion Pack","url":"http:\/\/twitter.com\/search?q=%22Expansion+Pack%22","promoted_content":null,"query":"%22Expansion+Pack%22","tweet_volume":11224},{"name":"\u8FFD\u52A0\u30B3\u30F3\u30C6\u30F3\u30C4","url":"http:\/\/twitter.com\/search?q=%E8%BF%BD%E5%8A%A0%E3%82%B3%E3%83%B3%E3%83%86%E3%83%B3%E3%83%84","promoted_content":null,"query":"%E8%BF%BD%E5%8A%A0%E3%82%B3%E3%83%B3%E3%83%86%E3%83%B3%E3%83%84","tweet_volume":49910},{"name":"WELCOME ZUU","url":"http:\/\/twitter.com\/search?q=%22WELCOME+ZUU%22","promoted_content":null,"query":"%22WELCOME+ZUU%22","tweet_volume":29447},{"name":"Dulceida","url":"http:\/\/twitter.com\/search?q=Dulceida","promoted_content":null,"query":"Dulceida","tweet_volume":null},{"name":"\u6709\u6599DLC","url":"http:\/\/twitter.com\/search?q=%E6%9C%89%E6%96%99DLC","promoted_content":null,"query":"%E6%9C%89%E6%96%99DLC","tweet_volume":null},{"name":"Lord Thakur","url":"http:\/\/twitter.com\/search?q=%22Lord+Thakur%22","promoted_content":null,"query":"%22Lord+Thakur%22","tweet_volume":null},{"name":"Atiba","url":"http:\/\/twitter.com\/search?q=Atiba","promoted_content":null,"query":"Atiba","tweet_volume":null},{"name":"AC DLC","url":"http:\/\/twitter.com\/search?q=%22AC+DLC%22","promoted_content":null,"query":"%22AC+DLC%22","tweet_volume":null},{"name":"SIGA LOUD VICTOR NO IG","url":"http:\/\/twitter.com\/search?q=%22SIGA+LOUD+VICTOR+NO+IG%22","promoted_content":null,"query":"%22SIGA+LOUD+VICTOR+NO+IG%22","tweet_volume":null},{"name":"Thug","url":"http:\/\/twitter.com\/search?q=Thug","promoted_content":null,"query":"Thug","tweet_volume":118555},{"name":"\u30CF\u30C3\u30D4\u30FC\u30DB\u30FC\u30E0\u30C7\u30B6\u30A4\u30CA\u30FC","url":"http:\/\/twitter.com\/search?q=%E3%83%8F%E3%83%83%E3%83%94%E3%83%BC%E3%83%9B%E3%83%BC%E3%83%A0%E3%83%87%E3%82%B6%E3%82%A4%E3%83%8A%E3%83%BC","promoted_content":null,"query":"%E3%83%8F%E3%83%83%E3%83%94%E3%83%BC%E3%83%9B%E3%83%BC%E3%83%A0%E3%83%87%E3%82%B6%E3%82%A4%E3%83%8A%E3%83%BC","tweet_volume":null},{"name":"Professores","url":"http:\/\/twitter.com\/search?q=Professores","promoted_content":null,"query":"Professores","tweet_volume":66521},{"name":"ZUU FIRE SATURDAY","url":"http:\/\/twitter.com\/search?q=%22ZUU+FIRE+SATURDAY%22","promoted_content":null,"query":"%22ZUU+FIRE+SATURDAY%22","tweet_volume":35845},{"name":"PRESAVE SG NOW","url":"http:\/\/twitter.com\/search?q=%22PRESAVE+SG+NOW%22","promoted_content":null,"query":"%22PRESAVE+SG+NOW%22","tweet_volume":13031},{"name":"Shino","url":"http:\/\/twitter.com\/search?q=Shino","promoted_content":null,"query":"Shino","tweet_volume":21656},{"name":"Suchmos","url":"http:\/\/twitter.com\/search?q=Suchmos","promoted_content":null,"query":"Suchmos","tweet_volume":26114},{"name":"Angela Rayner","url":"http:\/\/twitter.com\/search?q=%22Angela+Rayner%22","promoted_content":null,"query":"%22Angela+Rayner%22","tweet_volume":null},{"name":"New Leaf","url":"http:\/\/twitter.com\/search?q=%22New+Leaf%22","promoted_content":null,"query":"%22New+Leaf%22","tweet_volume":null},{"name":"Kocaeli CHP","url":"http:\/\/twitter.com\/search?q=%22Kocaeli+CHP%22","promoted_content":null,"query":"%22Kocaeli+CHP%22","tweet_volume":null},{"name":"#SVT_AUDIO_KIT","url":"http:\/\/twitter.com\/search?q=%23SVT_AUDIO_KIT","promoted_content":null,"query":"%23SVT_AUDIO_KIT","tweet_volume":97171}],"as_of":"2021-10-15T17:34:49Z","created_at":"2021-10-13T17:16:31Z","locations":[{"name":"Worldwide","woeid":1}]}]