[{"trends":[{"name":"\u30A2\u30B0\u30CD\u30B9\u30C7\u30B8\u30BF\u30EB","url":"http:\/\/twitter.com\/search?q=%E3%82%A2%E3%82%B0%E3%83%8D%E3%82%B9%E3%83%87%E3%82%B8%E3%82%BF%E3%83%AB","promoted_content":null,"query":"%E3%82%A2%E3%82%B0%E3%83%8D%E3%82%B9%E3%83%87%E3%82%B8%E3%82%BF%E3%83%AB","tweet_volume":42669},{"name":"\u30C7\u30B8\u305F\u3093","url":"http:\/\/twitter.com\/search?q=%E3%83%87%E3%82%B8%E3%81%9F%E3%82%93","promoted_content":null,"query":"%E3%83%87%E3%82%B8%E3%81%9F%E3%82%93","tweet_volume":35210},{"name":"#\u6771\u4EAC\u7AF6\u99AC\u5834","url":"http:\/\/twitter.com\/search?q=%23%E6%9D%B1%E4%BA%AC%E7%AB%B6%E9%A6%AC%E5%A0%B4","promoted_content":null,"query":"%23%E6%9D%B1%E4%BA%AC%E7%AB%B6%E9%A6%AC%E5%A0%B4","tweet_volume":null},{"name":"#ASAPkampeon","url":"http:\/\/twitter.com\/search?q=%23ASAPkampeon","promoted_content":null,"query":"%23ASAPkampeon","tweet_volume":232880},{"name":"#\u305D\u308C\u30B9\u30CE","url":"http:\/\/twitter.com\/search?q=%23%E3%81%9D%E3%82%8C%E3%82%B9%E3%83%8E","promoted_content":null,"query":"%23%E3%81%9D%E3%82%8C%E3%82%B9%E3%83%8E","tweet_volume":32587},{"name":"Remarkable DONBELLEonASAP","url":"http:\/\/twitter.com\/search?q=%22Remarkable+DONBELLEonASAP%22","promoted_content":null,"query":"%22Remarkable+DONBELLEonASAP%22","tweet_volume":256563},{"name":"#\u3048\u308B\u3059\u308A\u30FCDAY3","url":"http:\/\/twitter.com\/search?q=%23%E3%81%88%E3%82%8B%E3%81%99%E3%82%8A%E3%83%BCDAY3","promoted_content":null,"query":"%23%E3%81%88%E3%82%8B%E3%81%99%E3%82%8A%E3%83%BCDAY3","tweet_volume":11710},{"name":"Harvick","url":"http:\/\/twitter.com\/search?q=Harvick","promoted_content":null,"query":"Harvick","tweet_volume":11926},{"name":"#KFCXJennieGulf\u0E2A\u0E48\u0E07\u0E2A\u0E38\u0E02","url":"http:\/\/twitter.com\/search?q=%23KFCXJennieGulf%E0%B8%AA%E0%B9%88%E0%B8%87%E0%B8%AA%E0%B8%B8%E0%B8%82","promoted_content":null,"query":"%23KFCXJennieGulf%E0%B8%AA%E0%B9%88%E0%B8%87%E0%B8%AA%E0%B8%B8%E0%B8%82","tweet_volume":29412},{"name":"Auburn","url":"http:\/\/twitter.com\/search?q=Auburn","promoted_content":null,"query":"Auburn","tweet_volume":39173},{"name":"Penn State","url":"http:\/\/twitter.com\/search?q=%22Penn+State%22","promoted_content":null,"query":"%22Penn+State%22","tweet_volume":48347},{"name":"JULIETTE NO ALTAS HORAS","url":"http:\/\/twitter.com\/search?q=%22JULIETTE+NO+ALTAS+HORAS%22","promoted_content":null,"query":"%22JULIETTE+NO+ALTAS+HORAS%22","tweet_volume":81932},{"name":"\u6B66\u5668\u30AC\u30C1\u30E3","url":"http:\/\/twitter.com\/search?q=%E6%AD%A6%E5%99%A8%E3%82%AC%E3%83%81%E3%83%A3","promoted_content":null,"query":"%E6%AD%A6%E5%99%A8%E3%82%AC%E3%83%81%E3%83%A3","tweet_volume":null},{"name":"Fall For Nene","url":"http:\/\/twitter.com\/search?q=%22Fall+For+Nene%22","promoted_content":null,"query":"%22Fall+For+Nene%22","tweet_volume":97197},{"name":"\u30D5\u30EB\u30AB\u30E9\u30FC\u7279\u6B8APP","url":"http:\/\/twitter.com\/search?q=%E3%83%95%E3%83%AB%E3%82%AB%E3%83%A9%E3%83%BC%E7%89%B9%E6%AE%8APP","promoted_content":null,"query":"%E3%83%95%E3%83%AB%E3%82%AB%E3%83%A9%E3%83%BC%E7%89%B9%E6%AE%8APP","tweet_volume":null},{"name":"\u53F0\u98A8\u4E00\u904E","url":"http:\/\/twitter.com\/search?q=%E5%8F%B0%E9%A2%A8%E4%B8%80%E9%81%8E","promoted_content":null,"query":"%E5%8F%B0%E9%A2%A8%E4%B8%80%E9%81%8E","tweet_volume":37303},{"name":"UnforgettaBELLE OnASAP","url":"http:\/\/twitter.com\/search?q=%22UnforgettaBELLE+OnASAP%22","promoted_content":null,"query":"%22UnforgettaBELLE+OnASAP%22","tweet_volume":62437},{"name":"\u30BF\u30DE\u30E2\u30AF\u30ED\u30B9","url":"http:\/\/twitter.com\/search?q=%E3%82%BF%E3%83%9E%E3%83%A2%E3%82%AF%E3%83%AD%E3%82%B9","promoted_content":null,"query":"%E3%82%BF%E3%83%9E%E3%83%A2%E3%82%AF%E3%83%AD%E3%82%B9","tweet_volume":10088},{"name":"Chivas","url":"http:\/\/twitter.com\/search?q=Chivas","promoted_content":null,"query":"Chivas","tweet_volume":16096},{"name":"WELCOME TO NEW YORK","url":"http:\/\/twitter.com\/search?q=%22WELCOME+TO+NEW+YORK%22","promoted_content":null,"query":"%22WELCOME+TO+NEW+YORK%22","tweet_volume":46487},{"name":"BDAY DO GALEGUIN","url":"http:\/\/twitter.com\/search?q=%22BDAY+DO+GALEGUIN%22","promoted_content":null,"query":"%22BDAY+DO+GALEGUIN%22","tweet_volume":null},{"name":"Chase","url":"http:\/\/twitter.com\/search?q=Chase","promoted_content":null,"query":"Chase","tweet_volume":50719},{"name":"Bo Nix","url":"http:\/\/twitter.com\/search?q=%22Bo+Nix%22","promoted_content":null,"query":"%22Bo+Nix%22","tweet_volume":null},{"name":"JADE CUTTER","url":"http:\/\/twitter.com\/search?q=%22JADE+CUTTER%22","promoted_content":null,"query":"%22JADE+CUTTER%22","tweet_volume":null},{"name":"\u78D0\u5CA9\u7D50\u7DD1","url":"http:\/\/twitter.com\/search?q=%E7%A3%90%E5%B2%A9%E7%B5%90%E7%B7%91","promoted_content":null,"query":"%E7%A3%90%E5%B2%A9%E7%B5%90%E7%B7%91","tweet_volume":null},{"name":"Ole Miss","url":"http:\/\/twitter.com\/search?q=%22Ole+Miss%22","promoted_content":null,"query":"%22Ole+Miss%22","tweet_volume":null},{"name":"UCLA","url":"http:\/\/twitter.com\/search?q=UCLA","promoted_content":null,"query":"UCLA","tweet_volume":null},{"name":"Joui","url":"http:\/\/twitter.com\/search?q=Joui","promoted_content":null,"query":"Joui","tweet_volume":74545},{"name":"Machado","url":"http:\/\/twitter.com\/search?q=Machado","promoted_content":null,"query":"Machado","tweet_volume":13324},{"name":"Phil Davis","url":"http:\/\/twitter.com\/search?q=%22Phil+Davis%22","promoted_content":null,"query":"%22Phil+Davis%22","tweet_volume":null},{"name":"Dynho","url":"http:\/\/twitter.com\/search?q=Dynho","promoted_content":null,"query":"Dynho","tweet_volume":63032},{"name":"Toluca","url":"http:\/\/twitter.com\/search?q=Toluca","promoted_content":null,"query":"Toluca","tweet_volume":15624},{"name":"\u96F2\u3072\u3068\u3064","url":"http:\/\/twitter.com\/search?q=%E9%9B%B2%E3%81%B2%E3%81%A8%E3%81%A4","promoted_content":null,"query":"%E9%9B%B2%E3%81%B2%E3%81%A8%E3%81%A4","tweet_volume":null},{"name":"\u7121\u60E8\u306E\u8A55\u4FA1","url":"http:\/\/twitter.com\/search?q=%E7%84%A1%E6%83%A8%E3%81%AE%E8%A9%95%E4%BE%A1","promoted_content":null,"query":"%E7%84%A1%E6%83%A8%E3%81%AE%E8%A9%95%E4%BE%A1","tweet_volume":null},{"name":"BINIxBGYO PPOP CHAMPS","url":"http:\/\/twitter.com\/search?q=%22BINIxBGYO+PPOP+CHAMPS%22","promoted_content":null,"query":"%22BINIxBGYO+PPOP+CHAMPS%22","tweet_volume":44837},{"name":"Larson","url":"http:\/\/twitter.com\/search?q=Larson","promoted_content":null,"query":"Larson","tweet_volume":null},{"name":"\u4EBA\u51FA\u5897\u52A0","url":"http:\/\/twitter.com\/search?q=%E4%BA%BA%E5%87%BA%E5%A2%97%E5%8A%A0","promoted_content":null,"query":"%E4%BA%BA%E5%87%BA%E5%A2%97%E5%8A%A0","tweet_volume":null},{"name":"Fresno State","url":"http:\/\/twitter.com\/search?q=%22Fresno+State%22","promoted_content":null,"query":"%22Fresno+State%22","tweet_volume":null},{"name":"Boise State","url":"http:\/\/twitter.com\/search?q=%22Boise+State%22","promoted_content":null,"query":"%22Boise+State%22","tweet_volume":null},{"name":"Adult Swim","url":"http:\/\/twitter.com\/search?q=%22Adult+Swim%22","promoted_content":null,"query":"%22Adult+Swim%22","tweet_volume":null},{"name":"Tatis","url":"http:\/\/twitter.com\/search?q=Tatis","promoted_content":null,"query":"Tatis","tweet_volume":null},{"name":"Yedam","url":"http:\/\/twitter.com\/search?q=Yedam","promoted_content":null,"query":"Yedam","tweet_volume":25537},{"name":"DONNYKampeONATO SaASAP","url":"http:\/\/twitter.com\/search?q=%22DONNYKampeONATO+SaASAP%22","promoted_content":null,"query":"%22DONNYKampeONATO+SaASAP%22","tweet_volume":48526},{"name":"Yoel Romero","url":"http:\/\/twitter.com\/search?q=%22Yoel+Romero%22","promoted_content":null,"query":"%22Yoel+Romero%22","tweet_volume":null},{"name":"\u30ED\u30FC\u30BAS","url":"http:\/\/twitter.com\/search?q=%E3%83%AD%E3%83%BC%E3%82%BAS","promoted_content":null,"query":"%E3%83%AD%E3%83%BC%E3%82%BAS","tweet_volume":12965},{"name":"Matt Corral","url":"http:\/\/twitter.com\/search?q=%22Matt+Corral%22","promoted_content":null,"query":"%22Matt+Corral%22","tweet_volume":null},{"name":"Evidences Indicate SSR Murder","url":"http:\/\/twitter.com\/search?q=%22Evidences+Indicate+SSR+Murder%22","promoted_content":null,"query":"%22Evidences+Indicate+SSR+Murder%22","tweet_volume":16349},{"name":"GET READY FOR ARSOLO","url":"http:\/\/twitter.com\/search?q=%22GET+READY+FOR+ARSOLO%22","promoted_content":null,"query":"%22GET+READY+FOR+ARSOLO%22","tweet_volume":null},{"name":"\u5922\u306E\u901A\u308A\u9053","url":"http:\/\/twitter.com\/search?q=%E5%A4%A2%E3%81%AE%E9%80%9A%E3%82%8A%E9%81%93","promoted_content":null,"query":"%E5%A4%A2%E3%81%AE%E9%80%9A%E3%82%8A%E9%81%93","tweet_volume":null},{"name":"\u9AD8\u901F\u9053\u8DEF","url":"http:\/\/twitter.com\/search?q=%E9%AB%98%E9%80%9F%E9%81%93%E8%B7%AF","promoted_content":null,"query":"%E9%AB%98%E9%80%9F%E9%81%93%E8%B7%AF","tweet_volume":null}],"as_of":"2021-09-19T05:18:49Z","created_at":"2021-09-18T03:36:20Z","locations":[{"name":"Worldwide","woeid":1}]}]