[{"trends":[{"name":"#\u30C9\u30C3\u30AD\u30EAGP","url":"http:\/\/twitter.com\/search?q=%23%E3%83%89%E3%83%83%E3%82%AD%E3%83%AAGP","promoted_content":null,"query":"%23%E3%83%89%E3%83%83%E3%82%AD%E3%83%AAGP","tweet_volume":94085},{"name":"King Gnu","url":"http:\/\/twitter.com\/search?q=%22King+Gnu%22","promoted_content":null,"query":"%22King+Gnu%22","tweet_volume":33055},{"name":"#LIVBUR","url":"http:\/\/twitter.com\/search?q=%23LIVBUR","promoted_content":null,"query":"%23LIVBUR","tweet_volume":30993},{"name":"Burnley","url":"http:\/\/twitter.com\/search?q=Burnley","promoted_content":null,"query":"Burnley","tweet_volume":41464},{"name":"#81921CB23227","url":"http:\/\/twitter.com\/search?q=%2381921CB23227","promoted_content":null,"query":"%2381921CB23227","tweet_volume":58910},{"name":"#\u751F\u5F92\u304C\u4EBA\u751F\u3092\u3084\u308A\u76F4\u305B\u308B\u5B66\u6821","url":"http:\/\/twitter.com\/search?q=%23%E7%94%9F%E5%BE%92%E3%81%8C%E4%BA%BA%E7%94%9F%E3%82%92%E3%82%84%E3%82%8A%E7%9B%B4%E3%81%9B%E3%82%8B%E5%AD%A6%E6%A0%A1","promoted_content":null,"query":"%23%E7%94%9F%E5%BE%92%E3%81%8C%E4%BA%BA%E7%94%9F%E3%82%92%E3%82%84%E3%82%8A%E7%9B%B4%E3%81%9B%E3%82%8B%E5%AD%A6%E6%A0%A1","tweet_volume":41165},{"name":"\u30CA\u30F3\u30D0\u30AC","url":"http:\/\/twitter.com\/search?q=%E3%83%8A%E3%83%B3%E3%83%90%E3%82%AC","promoted_content":null,"query":"%E3%83%8A%E3%83%B3%E3%83%90%E3%82%AC","tweet_volume":14431},{"name":"#\u3042\u3056\u3068\u304F\u3066\u4F55\u304C\u60AA\u3044\u306E","url":"http:\/\/twitter.com\/search?q=%23%E3%81%82%E3%81%96%E3%81%A8%E3%81%8F%E3%81%A6%E4%BD%95%E3%81%8C%E6%82%AA%E3%81%84%E3%81%AE","promoted_content":null,"query":"%23%E3%81%82%E3%81%96%E3%81%A8%E3%81%8F%E3%81%A6%E4%BD%95%E3%81%8C%E6%82%AA%E3%81%84%E3%81%AE","tweet_volume":21097},{"name":"Liverpool","url":"http:\/\/twitter.com\/search?q=Liverpool","promoted_content":null,"query":"Liverpool","tweet_volume":78148},{"name":"ROVO","url":"http:\/\/twitter.com\/search?q=ROVO","promoted_content":null,"query":"ROVO","tweet_volume":null},{"name":"\u30CA\u30F3\u30D0\u30FC\u30AC\u30FC\u30EB","url":"http:\/\/twitter.com\/search?q=%E3%83%8A%E3%83%B3%E3%83%90%E3%83%BC%E3%82%AC%E3%83%BC%E3%83%AB","promoted_content":null,"query":"%E3%83%8A%E3%83%B3%E3%83%90%E3%83%BC%E3%82%AC%E3%83%BC%E3%83%AB","tweet_volume":null},{"name":"Jota","url":"http:\/\/twitter.com\/search?q=Jota","promoted_content":null,"query":"Jota","tweet_volume":26606},{"name":"Trent","url":"http:\/\/twitter.com\/search?q=Trent","promoted_content":null,"query":"Trent","tweet_volume":16487},{"name":"Harvey Elliot","url":"http:\/\/twitter.com\/search?q=%22Harvey+Elliot%22","promoted_content":null,"query":"%22Harvey+Elliot%22","tweet_volume":null},{"name":"INDOMY VOTING PARTY","url":"http:\/\/twitter.com\/search?q=%22INDOMY+VOTING+PARTY%22","promoted_content":null,"query":"%22INDOMY+VOTING+PARTY%22","tweet_volume":226143},{"name":"Mane","url":"http:\/\/twitter.com\/search?q=Mane","promoted_content":null,"query":"Mane","tweet_volume":45962},{"name":"NUMBER GIRL","url":"http:\/\/twitter.com\/search?q=%22NUMBER+GIRL%22","promoted_content":null,"query":"%22NUMBER+GIRL%22","tweet_volume":null},{"name":"Tsimikas","url":"http:\/\/twitter.com\/search?q=Tsimikas","promoted_content":null,"query":"Tsimikas","tweet_volume":14223},{"name":"Anfield","url":"http:\/\/twitter.com\/search?q=Anfield","promoted_content":null,"query":"Anfield","tweet_volume":37870},{"name":"\u900F\u660E\u5C11\u5973","url":"http:\/\/twitter.com\/search?q=%E9%80%8F%E6%98%8E%E5%B0%91%E5%A5%B3","promoted_content":null,"query":"%E9%80%8F%E6%98%8E%E5%B0%91%E5%A5%B3","tweet_volume":null},{"name":"The hole","url":"http:\/\/twitter.com\/search?q=%22The+hole%22","promoted_content":null,"query":"%22The+hole%22","tweet_volume":51847},{"name":"\u00D6zg\u00FCr Karabat","url":"http:\/\/twitter.com\/search?q=%22%C3%96zg%C3%BCr+Karabat%22","promoted_content":null,"query":"%22%C3%96zg%C3%BCr+Karabat%22","tweet_volume":null},{"name":"Prayer X","url":"http:\/\/twitter.com\/search?q=%22Prayer+X%22","promoted_content":null,"query":"%22Prayer+X%22","tweet_volume":null},{"name":"\u307E\u308A\u307B\u30FC","url":"http:\/\/twitter.com\/search?q=%E3%81%BE%E3%82%8A%E3%81%BB%E3%83%BC","promoted_content":null,"query":"%E3%81%BE%E3%82%8A%E3%81%BB%E3%83%BC","tweet_volume":null},{"name":"Van Dijk","url":"http:\/\/twitter.com\/search?q=%22Van+Dijk%22","promoted_content":null,"query":"%22Van+Dijk%22","tweet_volume":null},{"name":"\u6771\u4EAC\u30EA\u30D9\u30F3\u30B8\u30E3\u30FC\u30BA\u306E\u30AD\u30E3\u30E9","url":"http:\/\/twitter.com\/search?q=%E6%9D%B1%E4%BA%AC%E3%83%AA%E3%83%99%E3%83%B3%E3%82%B8%E3%83%A3%E3%83%BC%E3%82%BA%E3%81%AE%E3%82%AD%E3%83%A3%E3%83%A9","promoted_content":null,"query":"%E6%9D%B1%E4%BA%AC%E3%83%AA%E3%83%99%E3%83%B3%E3%82%B8%E3%83%A3%E3%83%BC%E3%82%BA%E3%81%AE%E3%82%AD%E3%83%A3%E3%83%A9","tweet_volume":null},{"name":"PERRIE","url":"http:\/\/twitter.com\/search?q=PERRIE","promoted_content":null,"query":"PERRIE","tweet_volume":10324},{"name":"RECORD SETTER JUNGKOOK","url":"http:\/\/twitter.com\/search?q=%22RECORD+SETTER+JUNGKOOK%22","promoted_content":null,"query":"%22RECORD+SETTER+JUNGKOOK%22","tweet_volume":77565},{"name":"\u30D0\u30CB\u30FC\u306E\u65E5","url":"http:\/\/twitter.com\/search?q=%E3%83%90%E3%83%8B%E3%83%BC%E3%81%AE%E6%97%A5","promoted_content":null,"query":"%E3%83%90%E3%83%8B%E3%83%BC%E3%81%AE%E6%97%A5","tweet_volume":89528},{"name":"Sadio","url":"http:\/\/twitter.com\/search?q=Sadio","promoted_content":null,"query":"Sadio","tweet_volume":null},{"name":"\u4E09\u6587\u5C0F\u8AAC","url":"http:\/\/twitter.com\/search?q=%E4%B8%89%E6%96%87%E5%B0%8F%E8%AA%AC","promoted_content":null,"query":"%E4%B8%89%E6%96%87%E5%B0%8F%E8%AA%AC","tweet_volume":null},{"name":"\u8061\u3061\u3083\u3093","url":"http:\/\/twitter.com\/search?q=%E8%81%A1%E3%81%A1%E3%82%83%E3%82%93","promoted_content":null,"query":"%E8%81%A1%E3%81%A1%E3%82%83%E3%82%93","tweet_volume":13741},{"name":"\u30A2\u30F3\u30B3\u30FC\u30EB","url":"http:\/\/twitter.com\/search?q=%E3%82%A2%E3%83%B3%E3%82%B3%E3%83%BC%E3%83%AB","promoted_content":null,"query":"%E3%82%A2%E3%83%B3%E3%82%B3%E3%83%BC%E3%83%AB","tweet_volume":11198},{"name":"NCT J","url":"http:\/\/twitter.com\/search?q=%22NCT+J%22","promoted_content":null,"query":"%22NCT+J%22","tweet_volume":31293},{"name":"Lord Adi","url":"http:\/\/twitter.com\/search?q=%22Lord+Adi%22","promoted_content":null,"query":"%22Lord+Adi%22","tweet_volume":null},{"name":"WIDEN THE GAP","url":"http:\/\/twitter.com\/search?q=%22WIDEN+THE+GAP%22","promoted_content":null,"query":"%22WIDEN+THE+GAP%22","tweet_volume":148635},{"name":"Dwight McNeil","url":"http:\/\/twitter.com\/search?q=%22Dwight+McNeil%22","promoted_content":null,"query":"%22Dwight+McNeil%22","tweet_volume":null},{"name":"\u3072\u3050\u3061\u541B","url":"http:\/\/twitter.com\/search?q=%E3%81%B2%E3%81%90%E3%81%A1%E5%90%9B","promoted_content":null,"query":"%E3%81%B2%E3%81%90%E3%81%A1%E5%90%9B","tweet_volume":null},{"name":"\u3059\u3044\u3061\u3083\u3093","url":"http:\/\/twitter.com\/search?q=%E3%81%99%E3%81%84%E3%81%A1%E3%82%83%E3%82%93","promoted_content":null,"query":"%E3%81%99%E3%81%84%E3%81%A1%E3%82%83%E3%82%93","tweet_volume":10307},{"name":"\u3072\u3050\u3061\u304F\u3093","url":"http:\/\/twitter.com\/search?q=%E3%81%B2%E3%81%90%E3%81%A1%E3%81%8F%E3%82%93","promoted_content":null,"query":"%E3%81%B2%E3%81%90%E3%81%A1%E3%81%8F%E3%82%93","tweet_volume":null},{"name":"\u4E95\u53E3\u3055\u3093","url":"http:\/\/twitter.com\/search?q=%E4%BA%95%E5%8F%A3%E3%81%95%E3%82%93","promoted_content":null,"query":"%E4%BA%95%E5%8F%A3%E3%81%95%E3%82%93","tweet_volume":null},{"name":"\u0635\u0644\u0627\u062D","url":"http:\/\/twitter.com\/search?q=%D8%B5%D9%84%D8%A7%D8%AD","promoted_content":null,"query":"%D8%B5%D9%84%D8%A7%D8%AD","tweet_volume":28186},{"name":"iremderici mambobeachte","url":"http:\/\/twitter.com\/search?q=%22iremderici+mambobeachte%22","promoted_content":null,"query":"%22iremderici+mambobeachte%22","tweet_volume":null},{"name":"\u4ED6\u4EBA\u306E\u305D\u3089\u4F3C","url":"http:\/\/twitter.com\/search?q=%E4%BB%96%E4%BA%BA%E3%81%AE%E3%81%9D%E3%82%89%E4%BC%BC","promoted_content":null,"query":"%E4%BB%96%E4%BA%BA%E3%81%AE%E3%81%9D%E3%82%89%E4%BC%BC","tweet_volume":null},{"name":"\u4E0D\u7834\u304F\u3093","url":"http:\/\/twitter.com\/search?q=%E4%B8%8D%E7%A0%B4%E3%81%8F%E3%82%93","promoted_content":null,"query":"%E4%B8%8D%E7%A0%B4%E3%81%8F%E3%82%93","tweet_volume":null},{"name":"\u30BD\u30ED\u30E9\u30A4\u30D6","url":"http:\/\/twitter.com\/search?q=%E3%82%BD%E3%83%AD%E3%83%A9%E3%82%A4%E3%83%96","promoted_content":null,"query":"%E3%82%BD%E3%83%AD%E3%83%A9%E3%82%A4%E3%83%96","tweet_volume":17249},{"name":"\u98A8\u78E8\u304F\u3093","url":"http:\/\/twitter.com\/search?q=%E9%A2%A8%E7%A3%A8%E3%81%8F%E3%82%93","promoted_content":null,"query":"%E9%A2%A8%E7%A3%A8%E3%81%8F%E3%82%93","tweet_volume":18932},{"name":"Keita","url":"http:\/\/twitter.com\/search?q=Keita","promoted_content":null,"query":"Keita","tweet_volume":11570},{"name":"\u6A39\u5C71\u5148\u751F","url":"http:\/\/twitter.com\/search?q=%E6%A8%B9%E5%B1%B1%E5%85%88%E7%94%9F","promoted_content":null,"query":"%E6%A8%B9%E5%B1%B1%E5%85%88%E7%94%9F","tweet_volume":null},{"name":"\u30BC\u30FC\u30F3\u3055\u3093","url":"http:\/\/twitter.com\/search?q=%E3%82%BC%E3%83%BC%E3%83%B3%E3%81%95%E3%82%93","promoted_content":null,"query":"%E3%82%BC%E3%83%BC%E3%83%B3%E3%81%95%E3%82%93","tweet_volume":null}],"as_of":"2021-08-21T13:20:12Z","created_at":"2021-08-20T03:49:10Z","locations":[{"name":"Worldwide","woeid":1}]}]