[{"trends":[{"name":"Faye","url":"http:\/\/twitter.com\/search?q=Faye","promoted_content":null,"query":"Faye","tweet_volume":176690},{"name":"#LoveIsland","url":"http:\/\/twitter.com\/search?q=%23LoveIsland","promoted_content":null,"query":"%23LoveIsland","tweet_volume":271914},{"name":"Teddy","url":"http:\/\/twitter.com\/search?q=Teddy","promoted_content":null,"query":"Teddy","tweet_volume":110967},{"name":"Jake","url":"http:\/\/twitter.com\/search?q=Jake","promoted_content":null,"query":"Jake","tweet_volume":161896},{"name":"#For\u00E7aBolsonaro","url":"http:\/\/twitter.com\/search?q=%23For%C3%A7aBolsonaro","promoted_content":null,"query":"%23For%C3%A7aBolsonaro","tweet_volume":74498},{"name":"#CashAppFriday","url":"http:\/\/twitter.com\/search?q=%23CashAppFriday","promoted_content":null,"query":"%23CashAppFriday","tweet_volume":null},{"name":"Frank Ocean","url":"http:\/\/twitter.com\/search?q=%22Frank+Ocean%22","promoted_content":null,"query":"%22Frank+Ocean%22","tweet_volume":13865},{"name":"#\u0645\u0633\u0627\u0628\u0642\u0647_\u0627\u0628\u0648\u0646\u0627\u0635\u0631","url":"http:\/\/twitter.com\/search?q=%23%D9%85%D8%B3%D8%A7%D8%A8%D9%82%D9%87_%D8%A7%D8%A8%D9%88%D9%86%D8%A7%D8%B5%D8%B1","promoted_content":null,"query":"%23%D9%85%D8%B3%D8%A7%D8%A8%D9%82%D9%87_%D8%A7%D8%A8%D9%88%D9%86%D8%A7%D8%B5%D8%B1","tweet_volume":197780},{"name":"#AliyeDon\u00F6rOl","url":"http:\/\/twitter.com\/search?q=%23AliyeDon%C3%B6rOl","promoted_content":null,"query":"%23AliyeDon%C3%B6rOl","tweet_volume":null},{"name":"Kenia","url":"http:\/\/twitter.com\/search?q=Kenia","promoted_content":null,"query":"Kenia","tweet_volume":31878},{"name":"Pote","url":"http:\/\/twitter.com\/search?q=Pote","promoted_content":null,"query":"Pote","tweet_volume":39275},{"name":"Juan de Dios","url":"http:\/\/twitter.com\/search?q=%22Juan+de+Dios%22","promoted_content":null,"query":"%22Juan+de+Dios%22","tweet_volume":23740},{"name":"Liberty","url":"http:\/\/twitter.com\/search?q=Liberty","promoted_content":null,"query":"Liberty","tweet_volume":41958},{"name":"Dave Grohl","url":"http:\/\/twitter.com\/search?q=%22Dave+Grohl%22","promoted_content":null,"query":"%22Dave+Grohl%22","tweet_volume":33034},{"name":"Grayson Allen","url":"http:\/\/twitter.com\/search?q=%22Grayson+Allen%22","promoted_content":null,"query":"%22Grayson+Allen%22","tweet_volume":null},{"name":"josh allen","url":"http:\/\/twitter.com\/search?q=%22josh+allen%22","promoted_content":null,"query":"%22josh+allen%22","tweet_volume":26196},{"name":"Pedro Gon\u00E7alves","url":"http:\/\/twitter.com\/search?q=%22Pedro+Gon%C3%A7alves%22","promoted_content":null,"query":"%22Pedro+Gon%C3%A7alves%22","tweet_volume":null},{"name":"Neymar","url":"http:\/\/twitter.com\/search?q=Neymar","promoted_content":null,"query":"Neymar","tweet_volume":230662},{"name":"Matthew","url":"http:\/\/twitter.com\/search?q=Matthew","promoted_content":null,"query":"Matthew","tweet_volume":40539},{"name":"Arthur Lira","url":"http:\/\/twitter.com\/search?q=%22Arthur+Lira%22","promoted_content":null,"query":"%22Arthur+Lira%22","tweet_volume":30602},{"name":"Bournemouth","url":"http:\/\/twitter.com\/search?q=Bournemouth","promoted_content":null,"query":"Bournemouth","tweet_volume":null},{"name":"DeJoy","url":"http:\/\/twitter.com\/search?q=DeJoy","promoted_content":null,"query":"DeJoy","tweet_volume":25492},{"name":"Utku","url":"http:\/\/twitter.com\/search?q=Utku","promoted_content":null,"query":"Utku","tweet_volume":null},{"name":"Bleach","url":"http:\/\/twitter.com\/search?q=Bleach","promoted_content":null,"query":"Bleach","tweet_volume":50748},{"name":"Jovane","url":"http:\/\/twitter.com\/search?q=Jovane","promoted_content":null,"query":"Jovane","tweet_volume":null},{"name":"Balotelli","url":"http:\/\/twitter.com\/search?q=Balotelli","promoted_content":null,"query":"Balotelli","tweet_volume":null},{"name":"Ashli Babbitt","url":"http:\/\/twitter.com\/search?q=%22Ashli+Babbitt%22","promoted_content":null,"query":"%22Ashli+Babbitt%22","tweet_volume":31244},{"name":"Vizela","url":"http:\/\/twitter.com\/search?q=Vizela","promoted_content":null,"query":"Vizela","tweet_volume":null},{"name":"Sporting","url":"http:\/\/twitter.com\/search?q=Sporting","promoted_content":null,"query":"Sporting","tweet_volume":82105},{"name":"\u062B\u0648\u0628 \u0627\u0644\u0645\u0631\u0648\u062F\u0646","url":"http:\/\/twitter.com\/search?q=%22%D8%AB%D9%88%D8%A8+%D8%A7%D9%84%D9%85%D8%B1%D9%88%D8%AF%D9%86%22","promoted_content":null,"query":"%22%D8%AB%D9%88%D8%A8+%D8%A7%D9%84%D9%85%D8%B1%D9%88%D8%AF%D9%86%22","tweet_volume":59838},{"name":"Elton John","url":"http:\/\/twitter.com\/search?q=%22Elton+John%22","promoted_content":null,"query":"%22Elton+John%22","tweet_volume":27712},{"name":"HARLEYS IN HAWAII","url":"http:\/\/twitter.com\/search?q=%22HARLEYS+IN+HAWAII%22","promoted_content":null,"query":"%22HARLEYS+IN+HAWAII%22","tweet_volume":24359},{"name":"ONE YEAR WITH TREASURE","url":"http:\/\/twitter.com\/search?q=%22ONE+YEAR+WITH+TREASURE%22","promoted_content":null,"query":"%22ONE+YEAR+WITH+TREASURE%22","tweet_volume":1383320},{"name":"Ligue 1","url":"http:\/\/twitter.com\/search?q=%22Ligue+1%22","promoted_content":null,"query":"%22Ligue+1%22","tweet_volume":52412},{"name":"S\u00FCfyaniGeldi BelaBitmiyor","url":"http:\/\/twitter.com\/search?q=%22S%C3%BCfyaniGeldi+BelaBitmiyor%22","promoted_content":null,"query":"%22S%C3%BCfyaniGeldi+BelaBitmiyor%22","tweet_volume":null},{"name":"Mbappe","url":"http:\/\/twitter.com\/search?q=Mbappe","promoted_content":null,"query":"Mbappe","tweet_volume":173199},{"name":"Chloe and Toby","url":"http:\/\/twitter.com\/search?q=%22Chloe+and+Toby%22","promoted_content":null,"query":"%22Chloe+and+Toby%22","tweet_volume":null},{"name":"Jia Tolentino","url":"http:\/\/twitter.com\/search?q=%22Jia+Tolentino%22","promoted_content":null,"query":"%22Jia+Tolentino%22","tweet_volume":null},{"name":"kyungsoo","url":"http:\/\/twitter.com\/search?q=kyungsoo","promoted_content":null,"query":"kyungsoo","tweet_volume":175103},{"name":"SUMMER OF LOVE IS COMING","url":"http:\/\/twitter.com\/search?q=%22SUMMER+OF+LOVE+IS+COMING%22","promoted_content":null,"query":"%22SUMMER+OF+LOVE+IS+COMING%22","tweet_volume":19566},{"name":"HAPPY 8900 DAYS LISA","url":"http:\/\/twitter.com\/search?q=%22HAPPY+8900+DAYS+LISA%22","promoted_content":null,"query":"%22HAPPY+8900+DAYS+LISA%22","tweet_volume":58323},{"name":"Fortaleza","url":"http:\/\/twitter.com\/search?q=Fortaleza","promoted_content":null,"query":"Fortaleza","tweet_volume":25042},{"name":"Copa do Brasil","url":"http:\/\/twitter.com\/search?q=%22Copa+do+Brasil%22","promoted_content":null,"query":"%22Copa+do+Brasil%22","tweet_volume":26401},{"name":"dominic fike","url":"http:\/\/twitter.com\/search?q=%22dominic+fike%22","promoted_content":null,"query":"%22dominic+fike%22","tweet_volume":null},{"name":"Nurse","url":"http:\/\/twitter.com\/search?q=Nurse","promoted_content":null,"query":"Nurse","tweet_volume":47787},{"name":"Rita Glavin","url":"http:\/\/twitter.com\/search?q=%22Rita+Glavin%22","promoted_content":null,"query":"%22Rita+Glavin%22","tweet_volume":null},{"name":"Nantes","url":"http:\/\/twitter.com\/search?q=Nantes","promoted_content":null,"query":"Nantes","tweet_volume":12419},{"name":"D\u00FCnya AlevAld\u0131","url":"http:\/\/twitter.com\/search?q=%22D%C3%BCnya+AlevAld%C4%B1%22","promoted_content":null,"query":"%22D%C3%BCnya+AlevAld%C4%B1%22","tweet_volume":null},{"name":"West Brom","url":"http:\/\/twitter.com\/search?q=%22West+Brom%22","promoted_content":null,"query":"%22West+Brom%22","tweet_volume":null},{"name":"Pferd","url":"http:\/\/twitter.com\/search?q=Pferd","promoted_content":null,"query":"Pferd","tweet_volume":17914}],"as_of":"2021-08-06T21:19:23Z","created_at":"2021-08-06T08:53:07Z","locations":[{"name":"Worldwide","woeid":1}]}]