[{"trends":[{"name":"Donda","url":"http:\/\/twitter.com\/search?q=Donda","promoted_content":null,"query":"Donda","tweet_volume":654009},{"name":"#WOLMUN","url":"http:\/\/twitter.com\/search?q=%23WOLMUN","promoted_content":null,"query":"%23WOLMUN","tweet_volume":135554},{"name":"#BelgianGP","url":"http:\/\/twitter.com\/search?q=%23BelgianGP","promoted_content":null,"query":"%23BelgianGP","tweet_volume":342266},{"name":"Kanye","url":"http:\/\/twitter.com\/search?q=Kanye","promoted_content":null,"query":"Kanye","tweet_volume":403260},{"name":"LALISA BY LISA","url":"http:\/\/twitter.com\/search?q=%22LALISA+BY+LISA%22","promoted_content":null,"query":"%22LALISA+BY+LISA%22","tweet_volume":548594},{"name":"#\u65E5\u5411\u5742\u3067\u4F1A\u3044\u307E\u3057\u3087\u3046","url":"http:\/\/twitter.com\/search?q=%23%E6%97%A5%E5%90%91%E5%9D%82%E3%81%A7%E4%BC%9A%E3%81%84%E3%81%BE%E3%81%97%E3%82%87%E3%81%86","promoted_content":null,"query":"%23%E6%97%A5%E5%90%91%E5%9D%82%E3%81%A7%E4%BC%9A%E3%81%84%E3%81%BE%E3%81%97%E3%82%87%E3%81%86","tweet_volume":26613},{"name":"Wolves","url":"http:\/\/twitter.com\/search?q=Wolves","promoted_content":null,"query":"Wolves","tweet_volume":141396},{"name":"#\u4E43\u6728\u5742\u5DE5\u4E8B\u4E2D","url":"http:\/\/twitter.com\/search?q=%23%E4%B9%83%E6%9C%A8%E5%9D%82%E5%B7%A5%E4%BA%8B%E4%B8%AD","promoted_content":null,"query":"%23%E4%B9%83%E6%9C%A8%E5%9D%82%E5%B7%A5%E4%BA%8B%E4%B8%AD","tweet_volume":30950},{"name":"#FileninSultanlar\u0131","url":"http:\/\/twitter.com\/search?q=%23FileninSultanlar%C4%B1","promoted_content":null,"query":"%23FileninSultanlar%C4%B1","tweet_volume":28071},{"name":"Varane","url":"http:\/\/twitter.com\/search?q=Varane","promoted_content":null,"query":"Varane","tweet_volume":99116},{"name":"Traore","url":"http:\/\/twitter.com\/search?q=Traore","promoted_content":null,"query":"Traore","tweet_volume":28253},{"name":"Sancho","url":"http:\/\/twitter.com\/search?q=Sancho","promoted_content":null,"query":"Sancho","tweet_volume":85176},{"name":"Souness","url":"http:\/\/twitter.com\/search?q=Souness","promoted_content":null,"query":"Souness","tweet_volume":13361},{"name":"De Gea","url":"http:\/\/twitter.com\/search?q=%22De+Gea%22","promoted_content":null,"query":"%22De+Gea%22","tweet_volume":19159},{"name":"Greenwood","url":"http:\/\/twitter.com\/search?q=Greenwood","promoted_content":null,"query":"Greenwood","tweet_volume":92943},{"name":"Griezmann","url":"http:\/\/twitter.com\/search?q=Griezmann","promoted_content":null,"query":"Griezmann","tweet_volume":31190},{"name":"Memphis","url":"http:\/\/twitter.com\/search?q=Memphis","promoted_content":null,"query":"Memphis","tweet_volume":69591},{"name":"PRE SAVE EP JULIETTE","url":"http:\/\/twitter.com\/search?q=%22PRE+SAVE+EP+JULIETTE%22","promoted_content":null,"query":"%22PRE+SAVE+EP+JULIETTE%22","tweet_volume":61542},{"name":"LISA THE SOLOIST","url":"http:\/\/twitter.com\/search?q=%22LISA+THE+SOLOIST%22","promoted_content":null,"query":"%22LISA+THE+SOLOIST%22","tweet_volume":117522},{"name":"Mike Dean","url":"http:\/\/twitter.com\/search?q=%22Mike+Dean%22","promoted_content":null,"query":"%22Mike+Dean%22","tweet_volume":10267},{"name":"Off The Grid","url":"http:\/\/twitter.com\/search?q=%22Off+The+Grid%22","promoted_content":null,"query":"%22Off+The+Grid%22","tweet_volume":45491},{"name":"Dan James","url":"http:\/\/twitter.com\/search?q=%22Dan+James%22","promoted_content":null,"query":"%22Dan+James%22","tweet_volume":13121},{"name":"Koeman","url":"http:\/\/twitter.com\/search?q=Koeman","promoted_content":null,"query":"Koeman","tweet_volume":35825},{"name":"Ed Asner","url":"http:\/\/twitter.com\/search?q=%22Ed+Asner%22","promoted_content":null,"query":"%22Ed+Asner%22","tweet_volume":19309},{"name":"Getafe","url":"http:\/\/twitter.com\/search?q=Getafe","promoted_content":null,"query":"Getafe","tweet_volume":34112},{"name":"Louisiana","url":"http:\/\/twitter.com\/search?q=Louisiana","promoted_content":null,"query":"Louisiana","tweet_volume":196209},{"name":"Diagne","url":"http:\/\/twitter.com\/search?q=Diagne","promoted_content":null,"query":"Diagne","tweet_volume":15441},{"name":"Jesus Lord","url":"http:\/\/twitter.com\/search?q=%22Jesus+Lord%22","promoted_content":null,"query":"%22Jesus+Lord%22","tweet_volume":31600},{"name":"Sergi Roberto","url":"http:\/\/twitter.com\/search?q=%22Sergi+Roberto%22","promoted_content":null,"query":"%22Sergi+Roberto%22","tweet_volume":11819},{"name":"Neves","url":"http:\/\/twitter.com\/search?q=Neves","promoted_content":null,"query":"Neves","tweet_volume":37989},{"name":"\u3059\u3057\u30BB\u30F3\u30BF\u30FC","url":"http:\/\/twitter.com\/search?q=%E3%81%99%E3%81%97%E3%82%BB%E3%83%B3%E3%82%BF%E3%83%BC","promoted_content":null,"query":"%E3%81%99%E3%81%97%E3%82%BB%E3%83%B3%E3%82%BF%E3%83%BC","tweet_volume":null},{"name":"Lee Scratch Perry","url":"http:\/\/twitter.com\/search?q=%22Lee+Scratch+Perry%22","promoted_content":null,"query":"%22Lee+Scratch+Perry%22","tweet_volume":22454},{"name":"Mazepin","url":"http:\/\/twitter.com\/search?q=Mazepin","promoted_content":null,"query":"Mazepin","tweet_volume":12025},{"name":"Grand Isle","url":"http:\/\/twitter.com\/search?q=%22Grand+Isle%22","promoted_content":null,"query":"%22Grand+Isle%22","tweet_volume":25612},{"name":"Get Fred","url":"http:\/\/twitter.com\/search?q=%22Get+Fred%22","promoted_content":null,"query":"%22Get+Fred%22","tweet_volume":null},{"name":"Al Roker","url":"http:\/\/twitter.com\/search?q=%22Al+Roker%22","promoted_content":null,"query":"%22Al+Roker%22","tweet_volume":null},{"name":"Jail","url":"http:\/\/twitter.com\/search?q=Jail","promoted_content":null,"query":"Jail","tweet_volume":122817},{"name":"\u062F\u064A\u0628\u0627\u064A","url":"http:\/\/twitter.com\/search?q=%D8%AF%D9%8A%D8%A8%D8%A7%D9%8A","promoted_content":null,"query":"%D8%AF%D9%8A%D8%A8%D8%A7%D9%8A","tweet_volume":null},{"name":"Lenglet","url":"http:\/\/twitter.com\/search?q=Lenglet","promoted_content":null,"query":"Lenglet","tweet_volume":null},{"name":"Seoul City","url":"http:\/\/twitter.com\/search?q=%22Seoul+City%22","promoted_content":null,"query":"%22Seoul+City%22","tweet_volume":307639},{"name":"Believe What I Say","url":"http:\/\/twitter.com\/search?q=%22Believe+What+I+Say%22","promoted_content":null,"query":"%22Believe+What+I+Say%22","tweet_volume":14004},{"name":"Donny","url":"http:\/\/twitter.com\/search?q=Donny","promoted_content":null,"query":"Donny","tweet_volume":114022},{"name":"Katrina","url":"http:\/\/twitter.com\/search?q=Katrina","promoted_content":null,"query":"Katrina","tweet_volume":66456},{"name":"\u30D1\u30E9\u5B66\u6821\u89B3\u6226","url":"http:\/\/twitter.com\/search?q=%E3%83%91%E3%83%A9%E5%AD%A6%E6%A0%A1%E8%A6%B3%E6%88%A6","promoted_content":null,"query":"%E3%83%91%E3%83%A9%E5%AD%A6%E6%A0%A1%E8%A6%B3%E6%88%A6","tweet_volume":27257},{"name":"Trincao","url":"http:\/\/twitter.com\/search?q=Trincao","promoted_content":null,"query":"Trincao","tweet_volume":null},{"name":"Daniel James","url":"http:\/\/twitter.com\/search?q=%22Daniel+James%22","promoted_content":null,"query":"%22Daniel+James%22","tweet_volume":11477},{"name":"LILO","url":"http:\/\/twitter.com\/search?q=LILO","promoted_content":null,"query":"LILO","tweet_volume":41165},{"name":"Fred and James","url":"http:\/\/twitter.com\/search?q=%22Fred+and+James%22","promoted_content":null,"query":"%22Fred+and+James%22","tweet_volume":null},{"name":"Fivio","url":"http:\/\/twitter.com\/search?q=Fivio","promoted_content":null,"query":"Fivio","tweet_volume":25115},{"name":"Checo","url":"http:\/\/twitter.com\/search?q=Checo","promoted_content":null,"query":"Checo","tweet_volume":33648}],"as_of":"2021-08-29T18:20:11Z","created_at":"2021-08-29T06:31:38Z","locations":[{"name":"Worldwide","woeid":1}]}]