[{"trends":[{"name":"#T\u00FCrkiyeYan\u0131yor","url":"http:\/\/twitter.com\/search?q=%23T%C3%BCrkiyeYan%C4%B1yor","promoted_content":null,"query":"%23T%C3%BCrkiyeYan%C4%B1yor","tweet_volume":185229},{"name":"jungkook","url":"http:\/\/twitter.com\/search?q=jungkook","promoted_content":null,"query":"jungkook","tweet_volume":2134941},{"name":"#AtesinCocuklar\u0131","url":"http:\/\/twitter.com\/search?q=%23AtesinCocuklar%C4%B1","promoted_content":null,"query":"%23AtesinCocuklar%C4%B1","tweet_volume":42966},{"name":"#PKKyakt\u0131","url":"http:\/\/twitter.com\/search?q=%23PKKyakt%C4%B1","promoted_content":null,"query":"%23PKKyakt%C4%B1","tweet_volume":210417},{"name":"#MANAVGATYAN\u0130YOR","url":"http:\/\/twitter.com\/search?q=%23MANAVGATYAN%C4%B0YOR","promoted_content":null,"query":"%23MANAVGATYAN%C4%B0YOR","tweet_volume":693963},{"name":"Guido Bellido","url":"http:\/\/twitter.com\/search?q=%22Guido+Bellido%22","promoted_content":null,"query":"%22Guido+Bellido%22","tweet_volume":23668},{"name":"#feydri","url":"http:\/\/twitter.com\/search?q=%23feydri","promoted_content":null,"query":"%23feydri","tweet_volume":null},{"name":"Pere","url":"http:\/\/twitter.com\/search?q=Pere","promoted_content":null,"query":"Pere","tweet_volume":44333},{"name":"\u7DD2\u65B9\u3055\u3093","url":"http:\/\/twitter.com\/search?q=%E7%B7%92%E6%96%B9%E3%81%95%E3%82%93","promoted_content":null,"query":"%E7%B7%92%E6%96%B9%E3%81%95%E3%82%93","tweet_volume":104893},{"name":"Londres","url":"http:\/\/twitter.com\/search?q=Londres","promoted_content":null,"query":"Londres","tweet_volume":58450},{"name":"Scarlett Johansson","url":"http:\/\/twitter.com\/search?q=%22Scarlett+Johansson%22","promoted_content":null,"query":"%22Scarlett+Johansson%22","tweet_volume":23273},{"name":"Jared Leto","url":"http:\/\/twitter.com\/search?q=%22Jared+Leto%22","promoted_content":null,"query":"%22Jared+Leto%22","tweet_volume":16406},{"name":"Rebeca","url":"http:\/\/twitter.com\/search?q=Rebeca","promoted_content":null,"query":"Rebeca","tweet_volume":859255},{"name":"Ayacucho","url":"http:\/\/twitter.com\/search?q=Ayacucho","promoted_content":null,"query":"Ayacucho","tweet_volume":15826},{"name":"Joey Votto","url":"http:\/\/twitter.com\/search?q=%22Joey+Votto%22","promoted_content":null,"query":"%22Joey+Votto%22","tweet_volume":15475},{"name":"Belalar BitecekMi","url":"http:\/\/twitter.com\/search?q=%22Belalar+BitecekMi%22","promoted_content":null,"query":"%22Belalar+BitecekMi%22","tweet_volume":null},{"name":"tom simons","url":"http:\/\/twitter.com\/search?q=%22tom+simons%22","promoted_content":null,"query":"%22tom+simons%22","tweet_volume":null},{"name":"Cerr\u00F3n","url":"http:\/\/twitter.com\/search?q=Cerr%C3%B3n","promoted_content":null,"query":"Cerr%C3%B3n","tweet_volume":46529},{"name":"Poyet","url":"http:\/\/twitter.com\/search?q=Poyet","promoted_content":null,"query":"Poyet","tweet_volume":null},{"name":"LIVE STREAM MILEYS SET","url":"http:\/\/twitter.com\/search?q=%22LIVE+STREAM+MILEYS+SET%22","promoted_content":null,"query":"%22LIVE+STREAM+MILEYS+SET%22","tweet_volume":15209},{"name":"ScarJo","url":"http:\/\/twitter.com\/search?q=ScarJo","promoted_content":null,"query":"ScarJo","tweet_volume":null},{"name":"Feyenoord","url":"http:\/\/twitter.com\/search?q=Feyenoord","promoted_content":null,"query":"Feyenoord","tweet_volume":null},{"name":"Louis Tomlinson","url":"http:\/\/twitter.com\/search?q=%22Louis+Tomlinson%22","promoted_content":null,"query":"%22Louis+Tomlinson%22","tweet_volume":365320},{"name":"Keita","url":"http:\/\/twitter.com\/search?q=Keita","promoted_content":null,"query":"Keita","tweet_volume":null},{"name":"THE LENA LUTHOR FOUNDATION","url":"http:\/\/twitter.com\/search?q=%22THE+LENA+LUTHOR+FOUNDATION%22","promoted_content":null,"query":"%22THE+LENA+LUTHOR+FOUNDATION%22","tweet_volume":null},{"name":"Jodie","url":"http:\/\/twitter.com\/search?q=Jodie","promoted_content":null,"query":"Jodie","tweet_volume":24808},{"name":"Castillo","url":"http:\/\/twitter.com\/search?q=Castillo","promoted_content":null,"query":"Castillo","tweet_volume":202237},{"name":"So What","url":"http:\/\/twitter.com\/search?q=%22So+What%22","promoted_content":null,"query":"%22So+What%22","tweet_volume":639412},{"name":"ALLAH BELANIZI VERS\u0130N","url":"http:\/\/twitter.com\/search?q=%22ALLAH+BELANIZI+VERS%C4%B0N%22","promoted_content":null,"query":"%22ALLAH+BELANIZI+VERS%C4%B0N%22","tweet_volume":24210},{"name":"Naby","url":"http:\/\/twitter.com\/search?q=Naby","promoted_content":null,"query":"Naby","tweet_volume":null},{"name":"Vlive","url":"http:\/\/twitter.com\/search?q=Vlive","promoted_content":null,"query":"Vlive","tweet_volume":377712},{"name":"FAR\u00CDAMOS TUDO NOVAMENTE","url":"http:\/\/twitter.com\/search?q=%22FAR%C3%8DAMOS+TUDO+NOVAMENTE%22","promoted_content":null,"query":"%22FAR%C3%8DAMOS+TUDO+NOVAMENTE%22","tweet_volume":16426},{"name":"A\u00E7\u0131kG\u00F6r\u00FC\u015F Engellenemez","url":"http:\/\/twitter.com\/search?q=%22A%C3%A7%C4%B1kG%C3%B6r%C3%BC%C5%9F+Engellenemez%22","promoted_content":null,"query":"%22A%C3%A7%C4%B1kG%C3%B6r%C3%BC%C5%9F+Engellenemez%22","tweet_volume":11479},{"name":"ABEL IS COMING","url":"http:\/\/twitter.com\/search?q=%22ABEL+IS+COMING%22","promoted_content":null,"query":"%22ABEL+IS+COMING%22","tweet_volume":null},{"name":"Daiane","url":"http:\/\/twitter.com\/search?q=Daiane","promoted_content":null,"query":"Daiane","tweet_volume":151259},{"name":"Komar","url":"http:\/\/twitter.com\/search?q=Komar","promoted_content":null,"query":"Komar","tweet_volume":null},{"name":"Minkah","url":"http:\/\/twitter.com\/search?q=Minkah","promoted_content":null,"query":"Minkah","tweet_volume":null},{"name":"Gerrit Cole","url":"http:\/\/twitter.com\/search?q=%22Gerrit+Cole%22","promoted_content":null,"query":"%22Gerrit+Cole%22","tweet_volume":null},{"name":"\u7DD2\u65B9\u6075\u7F8E\u3055\u3093","url":"http:\/\/twitter.com\/search?q=%E7%B7%92%E6%96%B9%E6%81%B5%E7%BE%8E%E3%81%95%E3%82%93","promoted_content":null,"query":"%E7%B7%92%E6%96%B9%E6%81%B5%E7%BE%8E%E3%81%95%E3%82%93","tweet_volume":41939},{"name":"OBX2 TOMORROW","url":"http:\/\/twitter.com\/search?q=%22OBX2+TOMORROW%22","promoted_content":null,"query":"%22OBX2+TOMORROW%22","tweet_volume":null},{"name":"Shake Shack","url":"http:\/\/twitter.com\/search?q=%22Shake+Shack%22","promoted_content":null,"query":"%22Shake+Shack%22","tweet_volume":null},{"name":"Kate Bishop","url":"http:\/\/twitter.com\/search?q=%22Kate+Bishop%22","promoted_content":null,"query":"%22Kate+Bishop%22","tweet_volume":10738},{"name":"Minamino","url":"http:\/\/twitter.com\/search?q=Minamino","promoted_content":null,"query":"Minamino","tweet_volume":null},{"name":"Chibnall","url":"http:\/\/twitter.com\/search?q=Chibnall","promoted_content":null,"query":"Chibnall","tweet_volume":12872},{"name":"Grealish","url":"http:\/\/twitter.com\/search?q=Grealish","promoted_content":null,"query":"Grealish","tweet_volume":19890},{"name":"Euphoria","url":"http:\/\/twitter.com\/search?q=Euphoria","promoted_content":null,"query":"Euphoria","tweet_volume":191439},{"name":"Abba Kyari","url":"http:\/\/twitter.com\/search?q=%22Abba+Kyari%22","promoted_content":null,"query":"%22Abba+Kyari%22","tweet_volume":99729},{"name":"Shams","url":"http:\/\/twitter.com\/search?q=Shams","promoted_content":null,"query":"Shams","tweet_volume":null},{"name":"Playdate","url":"http:\/\/twitter.com\/search?q=Playdate","promoted_content":null,"query":"Playdate","tweet_volume":null},{"name":"Biggie","url":"http:\/\/twitter.com\/search?q=Biggie","promoted_content":null,"query":"Biggie","tweet_volume":19474}],"as_of":"2021-07-29T19:30:50Z","created_at":"2021-07-28T14:31:19Z","locations":[{"name":"Worldwide","woeid":1}]}]