[{"trends":[{"name":"Google","url":"http:\/\/twitter.com\/search?q=Google","promoted_content":null,"query":"Google","tweet_volume":772995},{"name":"#KUSURABAKIYORUZ","url":"http:\/\/twitter.com\/search?q=%23KUSURABAKIYORUZ","promoted_content":null,"query":"%23KUSURABAKIYORUZ","tweet_volume":236289},{"name":"#DebateCHVCNN","url":"http:\/\/twitter.com\/search?q=%23DebateCHVCNN","promoted_content":null,"query":"%23DebateCHVCNN","tweet_volume":103600},{"name":"#EFMFandomxBrightLive","url":"http:\/\/twitter.com\/search?q=%23EFMFandomxBrightLive","promoted_content":null,"query":"%23EFMFandomxBrightLive","tweet_volume":189832},{"name":"#Philouday","url":"http:\/\/twitter.com\/search?q=%23Philouday","promoted_content":null,"query":"%23Philouday","tweet_volume":null},{"name":"\u30A2\u30F3\u30A4\u30F3\u30B9\u30C8\u30FC\u30EB","url":"http:\/\/twitter.com\/search?q=%E3%82%A2%E3%83%B3%E3%82%A4%E3%83%B3%E3%82%B9%E3%83%88%E3%83%BC%E3%83%AB","promoted_content":null,"query":"%E3%82%A2%E3%83%B3%E3%82%A4%E3%83%B3%E3%82%B9%E3%83%88%E3%83%BC%E3%83%AB","tweet_volume":null},{"name":"#\u4E00\u756A\u601D\u3044\u51FA\u306B\u6B8B\u3063\u3066\u3044\u308B\u30B2\u30FC\u30E0","url":"http:\/\/twitter.com\/search?q=%23%E4%B8%80%E7%95%AA%E6%80%9D%E3%81%84%E5%87%BA%E3%81%AB%E6%AE%8B%E3%81%A3%E3%81%A6%E3%81%84%E3%82%8B%E3%82%B2%E3%83%BC%E3%83%A0","promoted_content":null,"query":"%23%E4%B8%80%E7%95%AA%E6%80%9D%E3%81%84%E5%87%BA%E3%81%AB%E6%AE%8B%E3%81%A3%E3%81%A6%E3%81%84%E3%82%8B%E3%82%B2%E3%83%BC%E3%83%A0","tweet_volume":12173},{"name":"Bubblies ForeverWithDONBELLE","url":"http:\/\/twitter.com\/search?q=%22Bubblies+ForeverWithDONBELLE%22","promoted_content":null,"query":"%22Bubblies+ForeverWithDONBELLE%22","tweet_volume":70338},{"name":"Android\u52E2","url":"http:\/\/twitter.com\/search?q=Android%E5%8B%A2","promoted_content":null,"query":"Android%E5%8B%A2","tweet_volume":10479},{"name":"\u907A\u7269\u7DE9\u548C","url":"http:\/\/twitter.com\/search?q=%E9%81%BA%E7%89%A9%E7%B7%A9%E5%92%8C","promoted_content":null,"query":"%E9%81%BA%E7%89%A9%E7%B7%A9%E5%92%8C","tweet_volume":null},{"name":"FF9\u30A2\u30CB\u30E1\u5316","url":"http:\/\/twitter.com\/search?q=FF9%E3%82%A2%E3%83%8B%E3%83%A1%E5%8C%96","promoted_content":null,"query":"FF9%E3%82%A2%E3%83%8B%E3%83%A1%E5%8C%96","tweet_volume":39006},{"name":"\u5F37\u5236\u505C\u6B62","url":"http:\/\/twitter.com\/search?q=%E5%BC%B7%E5%88%B6%E5%81%9C%E6%AD%A2","promoted_content":null,"query":"%E5%BC%B7%E5%88%B6%E5%81%9C%E6%AD%A2","tweet_volume":null},{"name":"Usher","url":"http:\/\/twitter.com\/search?q=Usher","promoted_content":null,"query":"Usher","tweet_volume":44238},{"name":"\u4E0D\u5177\u5408\u767A\u751F","url":"http:\/\/twitter.com\/search?q=%E4%B8%8D%E5%85%B7%E5%90%88%E7%99%BA%E7%94%9F","promoted_content":null,"query":"%E4%B8%8D%E5%85%B7%E5%90%88%E7%99%BA%E7%94%9F","tweet_volume":null},{"name":"Crowder","url":"http:\/\/twitter.com\/search?q=Crowder","promoted_content":null,"query":"Crowder","tweet_volume":50543},{"name":"\u30B0\u30FC\u30B0\u30EB","url":"http:\/\/twitter.com\/search?q=%E3%82%B0%E3%83%BC%E3%82%B0%E3%83%AB","promoted_content":null,"query":"%E3%82%B0%E3%83%BC%E3%82%B0%E3%83%AB","tweet_volume":10222},{"name":"Lavin","url":"http:\/\/twitter.com\/search?q=Lavin","promoted_content":null,"query":"Lavin","tweet_volume":49564},{"name":"\u30A2\u30D7\u30EA\u60C5\u5831","url":"http:\/\/twitter.com\/search?q=%E3%82%A2%E3%83%97%E3%83%AA%E6%83%85%E5%A0%B1","promoted_content":null,"query":"%E3%82%A2%E3%83%97%E3%83%AA%E6%83%85%E5%A0%B1","tweet_volume":10490},{"name":"Briones","url":"http:\/\/twitter.com\/search?q=Briones","promoted_content":null,"query":"Briones","tweet_volume":21711},{"name":"\u907A\u72693\u500B","url":"http:\/\/twitter.com\/search?q=%E9%81%BA%E7%89%A93%E5%80%8B","promoted_content":null,"query":"%E9%81%BA%E7%89%A93%E5%80%8B","tweet_volume":null},{"name":"\u30A2\u30D7\u30EA\u7121\u52B9","url":"http:\/\/twitter.com\/search?q=%E3%82%A2%E3%83%97%E3%83%AA%E7%84%A1%E5%8A%B9","promoted_content":null,"query":"%E3%82%A2%E3%83%97%E3%83%AA%E7%84%A1%E5%8A%B9","tweet_volume":19189},{"name":"\u30ED\u30C3\u30AD\u30F3","url":"http:\/\/twitter.com\/search?q=%E3%83%AD%E3%83%83%E3%82%AD%E3%83%B3","promoted_content":null,"query":"%E3%83%AD%E3%83%83%E3%82%AD%E3%83%B3","tweet_volume":null},{"name":"FF:U","url":"http:\/\/twitter.com\/search?q=FF%3AU","promoted_content":null,"query":"FF%3AU","tweet_volume":null},{"name":"T-Pain","url":"http:\/\/twitter.com\/search?q=T-Pain","promoted_content":null,"query":"T-Pain","tweet_volume":51179},{"name":"Sichel","url":"http:\/\/twitter.com\/search?q=Sichel","promoted_content":null,"query":"Sichel","tweet_volume":27913},{"name":"Concordato","url":"http:\/\/twitter.com\/search?q=Concordato","promoted_content":null,"query":"Concordato","tweet_volume":null},{"name":"Android\u7AEF\u672B","url":"http:\/\/twitter.com\/search?q=Android%E7%AB%AF%E6%9C%AB","promoted_content":null,"query":"Android%E7%AB%AF%E6%9C%AB","tweet_volume":null},{"name":"\u9031\u5236\u9650\u64A4\u5EC3","url":"http:\/\/twitter.com\/search?q=%E9%80%B1%E5%88%B6%E9%99%90%E6%92%A4%E5%BB%83","promoted_content":null,"query":"%E9%80%B1%E5%88%B6%E9%99%90%E6%92%A4%E5%BB%83","tweet_volume":null},{"name":"BL\u30B7\u30A7\u30A2\u30CF\u30A6\u30B9","url":"http:\/\/twitter.com\/search?q=BL%E3%82%B7%E3%82%A7%E3%82%A2%E3%83%8F%E3%82%A6%E3%82%B9","promoted_content":null,"query":"BL%E3%82%B7%E3%82%A7%E3%82%A2%E3%83%8F%E3%82%A6%E3%82%B9","tweet_volume":14911},{"name":"\u767A\u751F\u78BA\u5B9F","url":"http:\/\/twitter.com\/search?q=%E7%99%BA%E7%94%9F%E7%A2%BA%E5%AE%9F","promoted_content":null,"query":"%E7%99%BA%E7%94%9F%E7%A2%BA%E5%AE%9F","tweet_volume":null},{"name":"\uCC9C\uB465\uBC88\uAC1C","url":"http:\/\/twitter.com\/search?q=%EC%B2%9C%EB%91%A5%EB%B2%88%EA%B0%9C","promoted_content":null,"query":"%EC%B2%9C%EB%91%A5%EB%B2%88%EA%B0%9C","tweet_volume":null},{"name":"\u4E94\u8F2A\u89B3\u6226\u5E30\u308A","url":"http:\/\/twitter.com\/search?q=%E4%BA%94%E8%BC%AA%E8%A6%B3%E6%88%A6%E5%B8%B0%E3%82%8A","promoted_content":null,"query":"%E4%BA%94%E8%BC%AA%E8%A6%B3%E6%88%A6%E5%B8%B0%E3%82%8A","tweet_volume":null},{"name":"\u6FC0\u30E4\u30D0\u306E8\u4F1A\u5834","url":"http:\/\/twitter.com\/search?q=%E6%BF%80%E3%83%A4%E3%83%90%E3%81%AE8%E4%BC%9A%E5%A0%B4","promoted_content":null,"query":"%E6%BF%80%E3%83%A4%E3%83%90%E3%81%AE8%E4%BC%9A%E5%A0%B4","tweet_volume":null},{"name":"CHOI YEONJUN","url":"http:\/\/twitter.com\/search?q=%22CHOI+YEONJUN%22","promoted_content":null,"query":"%22CHOI+YEONJUN%22","tweet_volume":null},{"name":"\u8D64\u6728\u30D5\u30A1\u30A4\u30EB","url":"http:\/\/twitter.com\/search?q=%E8%B5%A4%E6%9C%A8%E3%83%95%E3%82%A1%E3%82%A4%E3%83%AB","promoted_content":null,"query":"%E8%B5%A4%E6%9C%A8%E3%83%95%E3%82%A1%E3%82%A4%E3%83%AB","tweet_volume":31576},{"name":"\u9031\u5236\u9650\u89E3\u9664","url":"http:\/\/twitter.com\/search?q=%E9%80%B1%E5%88%B6%E9%99%90%E8%A7%A3%E9%99%A4","promoted_content":null,"query":"%E9%80%B1%E5%88%B6%E9%99%90%E8%A7%A3%E9%99%A4","tweet_volume":null},{"name":"\u30DE\u30A6\u30F3\u30C6\u30F3","url":"http:\/\/twitter.com\/search?q=%E3%83%9E%E3%82%A6%E3%83%B3%E3%83%86%E3%83%B3","promoted_content":null,"query":"%E3%83%9E%E3%82%A6%E3%83%B3%E3%83%86%E3%83%B3","tweet_volume":null},{"name":"\u30DD\u30C3\u30D7\u30A2\u30C3\u30D7","url":"http:\/\/twitter.com\/search?q=%E3%83%9D%E3%83%83%E3%83%97%E3%82%A2%E3%83%83%E3%83%97","promoted_content":null,"query":"%E3%83%9D%E3%83%83%E3%83%97%E3%82%A2%E3%83%83%E3%83%97","tweet_volume":10667},{"name":"BUBBLIES NEVER PIRATED HIH","url":"http:\/\/twitter.com\/search?q=%22BUBBLIES+NEVER+PIRATED+HIH%22","promoted_content":null,"query":"%22BUBBLIES+NEVER+PIRATED+HIH%22","tweet_volume":null},{"name":"\u548C\u4E45\u4E95\u3055\u3093","url":"http:\/\/twitter.com\/search?q=%E5%92%8C%E4%B9%85%E4%BA%95%E3%81%95%E3%82%93","promoted_content":null,"query":"%E5%92%8C%E4%B9%85%E4%BA%95%E3%81%95%E3%82%93","tweet_volume":null},{"name":"\u79C1\u306E\u30B9\u30DE\u30DB","url":"http:\/\/twitter.com\/search?q=%E7%A7%81%E3%81%AE%E3%82%B9%E3%83%9E%E3%83%9B","promoted_content":null,"query":"%E7%A7%81%E3%81%AE%E3%82%B9%E3%83%9E%E3%83%9B","tweet_volume":null},{"name":"\u30DA\u30D7\u30B7\u30DE\u30F3","url":"http:\/\/twitter.com\/search?q=%E3%83%9A%E3%83%97%E3%82%B7%E3%83%9E%E3%83%B3","promoted_content":null,"query":"%E3%83%9A%E3%83%97%E3%82%B7%E3%83%9E%E3%83%B3","tweet_volume":null},{"name":"No Mercy 4 Sushant Killers","url":"http:\/\/twitter.com\/search?q=%22No+Mercy+4+Sushant+Killers%22","promoted_content":null,"query":"%22No+Mercy+4+Sushant+Killers%22","tweet_volume":83025},{"name":"\u30D0\u30C3\u30AF\u30A2\u30C3\u30D7\u30E1\u30F3\u30D0\u30FC","url":"http:\/\/twitter.com\/search?q=%E3%83%90%E3%83%83%E3%82%AF%E3%82%A2%E3%83%83%E3%83%97%E3%83%A1%E3%83%B3%E3%83%90%E3%83%BC","promoted_content":null,"query":"%E3%83%90%E3%83%83%E3%82%AF%E3%82%A2%E3%83%83%E3%83%97%E3%83%A1%E3%83%B3%E3%83%90%E3%83%BC","tweet_volume":null},{"name":"\u30B0\u30F3\u30D2\u30EB\u30C9\u30FB\u30C7\u30A3\u30EB\u30FC\u30D6\u30E9\u30E0","url":"http:\/\/twitter.com\/search?q=%E3%82%B0%E3%83%B3%E3%83%92%E3%83%AB%E3%83%89%E3%83%BB%E3%83%87%E3%82%A3%E3%83%AB%E3%83%BC%E3%83%96%E3%83%A9%E3%83%A0","promoted_content":null,"query":"%E3%82%B0%E3%83%B3%E3%83%92%E3%83%AB%E3%83%89%E3%83%BB%E3%83%87%E3%82%A3%E3%83%AB%E3%83%BC%E3%83%96%E3%83%A9%E3%83%A0","tweet_volume":null},{"name":"\u30A2\u30D7\u30EA\u66F4\u65B0","url":"http:\/\/twitter.com\/search?q=%E3%82%A2%E3%83%97%E3%83%AA%E6%9B%B4%E6%96%B0","promoted_content":null,"query":"%E3%82%A2%E3%83%97%E3%83%AA%E6%9B%B4%E6%96%B0","tweet_volume":11171},{"name":"Dirgahayu Jakarta","url":"http:\/\/twitter.com\/search?q=%22Dirgahayu+Jakarta%22","promoted_content":null,"query":"%22Dirgahayu+Jakarta%22","tweet_volume":null},{"name":"JU HAKNYEON","url":"http:\/\/twitter.com\/search?q=%22JU+HAKNYEON%22","promoted_content":null,"query":"%22JU+HAKNYEON%22","tweet_volume":50507},{"name":"\u4E09\u91CD\u770C\u5EC3\u6B62","url":"http:\/\/twitter.com\/search?q=%E4%B8%89%E9%87%8D%E7%9C%8C%E5%BB%83%E6%AD%A2","promoted_content":null,"query":"%E4%B8%89%E9%87%8D%E7%9C%8C%E5%BB%83%E6%AD%A2","tweet_volume":null},{"name":"Play\u30B9\u30C8\u30A2","url":"http:\/\/twitter.com\/search?q=Play%E3%82%B9%E3%83%88%E3%82%A2","promoted_content":null,"query":"Play%E3%82%B9%E3%83%88%E3%82%A2","tweet_volume":null}],"as_of":"2021-06-22T07:34:17Z","created_at":"2021-06-21T08:52:57Z","locations":[{"name":"Worldwide","woeid":1}]}]