[{"trends":[{"name":"#\u30D7\u30ED\u30BB\u30AB\u751F\u653E\u9001","url":"http:\/\/twitter.com\/search?q=%23%E3%83%97%E3%83%AD%E3%82%BB%E3%82%AB%E7%94%9F%E6%94%BE%E9%80%81","promoted_content":null,"query":"%23%E3%83%97%E3%83%AD%E3%82%BB%E3%82%AB%E7%94%9F%E6%94%BE%E9%80%81","tweet_volume":60387},{"name":"\u592B\u5A66\u306E\u65E5","url":"http:\/\/twitter.com\/search?q=%E5%A4%AB%E5%A9%A6%E3%81%AE%E6%97%A5","promoted_content":null,"query":"%E5%A4%AB%E5%A9%A6%E3%81%AE%E6%97%A5","tweet_volume":207554},{"name":"#\u3044\u3044\u30C4\u30A4\u30F3\u30C6\u30FC\u30EB\u306E\u65E5","url":"http:\/\/twitter.com\/search?q=%23%E3%81%84%E3%81%84%E3%83%84%E3%82%A4%E3%83%B3%E3%83%86%E3%83%BC%E3%83%AB%E3%81%AE%E6%97%A5","promoted_content":null,"query":"%23%E3%81%84%E3%81%84%E3%83%84%E3%82%A4%E3%83%B3%E3%83%86%E3%83%BC%E3%83%AB%E3%81%AE%E6%97%A5","tweet_volume":141294},{"name":"Shenhe","url":"http:\/\/twitter.com\/search?q=Shenhe","promoted_content":null,"query":"Shenhe","tweet_volume":64491},{"name":"#\u0645\u0627\u0643_\u062A\u062F\u0639\u0645_\u0630\u0648\u064A_\u0645\u062A\u0644\u0627\u0632\u0645\u0647_\u062F\u0627\u0648\u0646","url":"http:\/\/twitter.com\/search?q=%23%D9%85%D8%A7%D9%83_%D8%AA%D8%AF%D8%B9%D9%85_%D8%B0%D9%88%D9%8A_%D9%85%D8%AA%D9%84%D8%A7%D8%B2%D9%85%D9%87_%D8%AF%D8%A7%D9%88%D9%86","promoted_content":null,"query":"%23%D9%85%D8%A7%D9%83_%D8%AA%D8%AF%D8%B9%D9%85_%D8%B0%D9%88%D9%8A_%D9%85%D8%AA%D9%84%D8%A7%D8%B2%D9%85%D9%87_%D8%AF%D8%A7%D9%88%D9%86","tweet_volume":null},{"name":"#MondayMotivation","url":"http:\/\/twitter.com\/search?q=%23MondayMotivation","promoted_content":null,"query":"%23MondayMotivation","tweet_volume":35619},{"name":"#\u5E30\u308C\u30DE\u30F3\u30C7\u30FC","url":"http:\/\/twitter.com\/search?q=%23%E5%B8%B0%E3%82%8C%E3%83%9E%E3%83%B3%E3%83%87%E3%83%BC","promoted_content":null,"query":"%23%E5%B8%B0%E3%82%8C%E3%83%9E%E3%83%B3%E3%83%87%E3%83%BC","tweet_volume":19407},{"name":"HIHMovieCut OnIWantTFC","url":"http:\/\/twitter.com\/search?q=%22HIHMovieCut+OnIWantTFC%22","promoted_content":null,"query":"%22HIHMovieCut+OnIWantTFC%22","tweet_volume":21239},{"name":"Stell MA NASAAN","url":"http:\/\/twitter.com\/search?q=%22Stell+MA+NASAAN%22","promoted_content":null,"query":"%22Stell+MA+NASAAN%22","tweet_volume":20158},{"name":"\u897F\u6CA2\u3055\u3093","url":"http:\/\/twitter.com\/search?q=%E8%A5%BF%E6%B2%A2%E3%81%95%E3%82%93","promoted_content":null,"query":"%E8%A5%BF%E6%B2%A2%E3%81%95%E3%82%93","tweet_volume":null},{"name":"\u65B0\u30AD\u30E3\u30E9","url":"http:\/\/twitter.com\/search?q=%E6%96%B0%E3%82%AD%E3%83%A3%E3%83%A9","promoted_content":null,"query":"%E6%96%B0%E3%82%AD%E3%83%A3%E3%83%A9","tweet_volume":23964},{"name":"\u6709\u6A5F\u9178\u3055\u3093","url":"http:\/\/twitter.com\/search?q=%E6%9C%89%E6%A9%9F%E9%85%B8%E3%81%95%E3%82%93","promoted_content":null,"query":"%E6%9C%89%E6%A9%9F%E9%85%B8%E3%81%95%E3%82%93","tweet_volume":null},{"name":"Yun Jin","url":"http:\/\/twitter.com\/search?q=%22Yun+Jin%22","promoted_content":null,"query":"%22Yun+Jin%22","tweet_volume":29441},{"name":"\u6C96\u7530\u3055\u3093","url":"http:\/\/twitter.com\/search?q=%E6%B2%96%E7%94%B0%E3%81%95%E3%82%93","promoted_content":null,"query":"%E6%B2%96%E7%94%B0%E3%81%95%E3%82%93","tweet_volume":null},{"name":"Golden Boy","url":"http:\/\/twitter.com\/search?q=%22Golden+Boy%22","promoted_content":null,"query":"%22Golden+Boy%22","tweet_volume":22281},{"name":"Peppa Pig World","url":"http:\/\/twitter.com\/search?q=%22Peppa+Pig+World%22","promoted_content":null,"query":"%22Peppa+Pig+World%22","tweet_volume":null},{"name":"\u7533\u9DB4\u3055\u3093","url":"http:\/\/twitter.com\/search?q=%E7%94%B3%E9%B6%B4%E3%81%95%E3%82%93","promoted_content":null,"query":"%E7%94%B3%E9%B6%B4%E3%81%95%E3%82%93","tweet_volume":null},{"name":"\u30B9\u30BF\u30DE\u30B9","url":"http:\/\/twitter.com\/search?q=%E3%82%B9%E3%82%BF%E3%83%9E%E3%82%B9","promoted_content":null,"query":"%E3%82%B9%E3%82%BF%E3%83%9E%E3%82%B9","tweet_volume":15904},{"name":"\u96F2\u83EB\u3061\u3083\u3093","url":"http:\/\/twitter.com\/search?q=%E9%9B%B2%E8%8F%AB%E3%81%A1%E3%82%83%E3%82%93","promoted_content":null,"query":"%E9%9B%B2%E8%8F%AB%E3%81%A1%E3%82%83%E3%82%93","tweet_volume":null},{"name":"\u6728\u4E0B\u5BCC\u7F8E\u5B50\u90FD\u8B70","url":"http:\/\/twitter.com\/search?q=%E6%9C%A8%E4%B8%8B%E5%AF%8C%E7%BE%8E%E5%AD%90%E9%83%BD%E8%AD%B0","promoted_content":null,"query":"%E6%9C%A8%E4%B8%8B%E5%AF%8C%E7%BE%8E%E5%AD%90%E9%83%BD%E8%AD%B0","tweet_volume":null},{"name":"Santa Cecilia","url":"http:\/\/twitter.com\/search?q=%22Santa+Cecilia%22","promoted_content":null,"query":"%22Santa+Cecilia%22","tweet_volume":null},{"name":"\u5742\u672C\u9F8D\u99AC","url":"http:\/\/twitter.com\/search?q=%E5%9D%82%E6%9C%AC%E9%BE%8D%E9%A6%AC","promoted_content":null,"query":"%E5%9D%82%E6%9C%AC%E9%BE%8D%E9%A6%AC","tweet_volume":62538},{"name":"\u52E4\u52B4\u611F\u8B1D\u306E\u65E5","url":"http:\/\/twitter.com\/search?q=%E5%8B%A4%E5%8A%B4%E6%84%9F%E8%AC%9D%E3%81%AE%E6%97%A5","promoted_content":null,"query":"%E5%8B%A4%E5%8A%B4%E6%84%9F%E8%AC%9D%E3%81%AE%E6%97%A5","tweet_volume":33967},{"name":"\u7389\u888B\u3086\u305F\u304B","url":"http:\/\/twitter.com\/search?q=%E7%8E%89%E8%A2%8B%E3%82%86%E3%81%9F%E3%81%8B","promoted_content":null,"query":"%E7%8E%89%E8%A2%8B%E3%82%86%E3%81%9F%E3%81%8B","tweet_volume":92894},{"name":"Shahrukh Khan","url":"http:\/\/twitter.com\/search?q=%22Shahrukh+Khan%22","promoted_content":null,"query":"%22Shahrukh+Khan%22","tweet_volume":null},{"name":"\u5742\u672C\u3055\u3093","url":"http:\/\/twitter.com\/search?q=%E5%9D%82%E6%9C%AC%E3%81%95%E3%82%93","promoted_content":null,"query":"%E5%9D%82%E6%9C%AC%E3%81%95%E3%82%93","tweet_volume":20970},{"name":"Herkes Zengin","url":"http:\/\/twitter.com\/search?q=%22Herkes+Zengin%22","promoted_content":null,"query":"%22Herkes+Zengin%22","tweet_volume":null},{"name":"\u30B8\u30E3\u30CB\u30A2\u30A4","url":"http:\/\/twitter.com\/search?q=%E3%82%B8%E3%83%A3%E3%83%8B%E3%82%A2%E3%82%A4","promoted_content":null,"query":"%E3%82%B8%E3%83%A3%E3%83%8B%E3%82%A2%E3%82%A4","tweet_volume":12168},{"name":"\u30D5\u30A7\u30CB\u30FC\u304F\u3093","url":"http:\/\/twitter.com\/search?q=%E3%83%95%E3%82%A7%E3%83%8B%E3%83%BC%E3%81%8F%E3%82%93","promoted_content":null,"query":"%E3%83%95%E3%82%A7%E3%83%8B%E3%83%BC%E3%81%8F%E3%82%93","tweet_volume":null},{"name":"SF9 TRAUMA OUT NOW","url":"http:\/\/twitter.com\/search?q=%22SF9+TRAUMA+OUT+NOW%22","promoted_content":null,"query":"%22SF9+TRAUMA+OUT+NOW%22","tweet_volume":40824},{"name":"M-1\u30B0\u30E9\u30F3\u30D7\u30EA","url":"http:\/\/twitter.com\/search?q=M-1%E3%82%B0%E3%83%A9%E3%83%B3%E3%83%97%E3%83%AA","promoted_content":null,"query":"M-1%E3%82%B0%E3%83%A9%E3%83%B3%E3%83%97%E3%83%AA","tweet_volume":null},{"name":"\u9F8D\u99AC\u3055\u3093","url":"http:\/\/twitter.com\/search?q=%E9%BE%8D%E9%A6%AC%E3%81%95%E3%82%93","promoted_content":null,"query":"%E9%BE%8D%E9%A6%AC%E3%81%95%E3%82%93","tweet_volume":25886},{"name":"\u7121\u514D\u8A31\u904B\u8EE2","url":"http:\/\/twitter.com\/search?q=%E7%84%A1%E5%85%8D%E8%A8%B1%E9%81%8B%E8%BB%A2","promoted_content":null,"query":"%E7%84%A1%E5%85%8D%E8%A8%B1%E9%81%8B%E8%BB%A2","tweet_volume":14714},{"name":"\u6E96\u3005\u6C7A\u52DD","url":"http:\/\/twitter.com\/search?q=%E6%BA%96%E3%80%85%E6%B1%BA%E5%8B%9D","promoted_content":null,"query":"%E6%BA%96%E3%80%85%E6%B1%BA%E5%8B%9D","tweet_volume":null},{"name":"CELEBRATING EUNKWANG DAY","url":"http:\/\/twitter.com\/search?q=%22CELEBRATING+EUNKWANG+DAY%22","promoted_content":null,"query":"%22CELEBRATING+EUNKWANG+DAY%22","tweet_volume":null},{"name":"\u69CD\u30AD\u30E3\u30E9","url":"http:\/\/twitter.com\/search?q=%E6%A7%8D%E3%82%AD%E3%83%A3%E3%83%A9","promoted_content":null,"query":"%E6%A7%8D%E3%82%AD%E3%83%A3%E3%83%A9","tweet_volume":null},{"name":"TOKOTOKO\u3055\u3093","url":"http:\/\/twitter.com\/search?q=TOKOTOKO%E3%81%95%E3%82%93","promoted_content":null,"query":"TOKOTOKO%E3%81%95%E3%82%93","tweet_volume":null},{"name":"\u30B3\u30CD\u30AF\u30C8\u30E9\u30A4\u30D6","url":"http:\/\/twitter.com\/search?q=%E3%82%B3%E3%83%8D%E3%82%AF%E3%83%88%E3%83%A9%E3%82%A4%E3%83%96","promoted_content":null,"query":"%E3%82%B3%E3%83%8D%E3%82%AF%E3%83%88%E3%83%A9%E3%82%A4%E3%83%96","tweet_volume":null},{"name":"Poch","url":"http:\/\/twitter.com\/search?q=Poch","promoted_content":null,"query":"Poch","tweet_volume":19418},{"name":"\u516B\u91CD\u795E\u5B50","url":"http:\/\/twitter.com\/search?q=%E5%85%AB%E9%87%8D%E7%A5%9E%E5%AD%90","promoted_content":null,"query":"%E5%85%AB%E9%87%8D%E7%A5%9E%E5%AD%90","tweet_volume":null},{"name":"\u30E2\u30E2\u30B8\u30E3\u30F3","url":"http:\/\/twitter.com\/search?q=%E3%83%A2%E3%83%A2%E3%82%B8%E3%83%A3%E3%83%B3","promoted_content":null,"query":"%E3%83%A2%E3%83%A2%E3%82%B8%E3%83%A3%E3%83%B3","tweet_volume":null},{"name":"Itto","url":"http:\/\/twitter.com\/search?q=Itto","promoted_content":null,"query":"Itto","tweet_volume":84876},{"name":"\u30E9\u30F3\u30B5\u30FC","url":"http:\/\/twitter.com\/search?q=%E3%83%A9%E3%83%B3%E3%82%B5%E3%83%BC","promoted_content":null,"query":"%E3%83%A9%E3%83%B3%E3%82%B5%E3%83%BC","tweet_volume":54695},{"name":"\u65B0\u5200\u5263\u7537\u58EB","url":"http:\/\/twitter.com\/search?q=%E6%96%B0%E5%88%80%E5%89%A3%E7%94%B7%E5%A3%AB","promoted_content":null,"query":"%E6%96%B0%E5%88%80%E5%89%A3%E7%94%B7%E5%A3%AB","tweet_volume":14603},{"name":"\u30A2\u30B8\u30AB\u30F3","url":"http:\/\/twitter.com\/search?q=%E3%82%A2%E3%82%B8%E3%82%AB%E3%83%B3","promoted_content":null,"query":"%E3%82%A2%E3%82%B8%E3%82%AB%E3%83%B3","tweet_volume":null},{"name":"\u9762\u5F71\u3055\u3093","url":"http:\/\/twitter.com\/search?q=%E9%9D%A2%E5%BD%B1%E3%81%95%E3%82%93","promoted_content":null,"query":"%E9%9D%A2%E5%BD%B1%E3%81%95%E3%82%93","tweet_volume":null},{"name":"\u8F9E\u8077\u306E\u610F\u5411","url":"http:\/\/twitter.com\/search?q=%E8%BE%9E%E8%81%B7%E3%81%AE%E6%84%8F%E5%90%91","promoted_content":null,"query":"%E8%BE%9E%E8%81%B7%E3%81%AE%E6%84%8F%E5%90%91","tweet_volume":null},{"name":"\u3066\u3089\u3057\u30FC","url":"http:\/\/twitter.com\/search?q=%E3%81%A6%E3%82%89%E3%81%97%E3%83%BC","promoted_content":null,"query":"%E3%81%A6%E3%82%89%E3%81%97%E3%83%BC","tweet_volume":null},{"name":"YESEO FOR DAZED","url":"http:\/\/twitter.com\/search?q=%22YESEO+FOR+DAZED%22","promoted_content":null,"query":"%22YESEO+FOR+DAZED%22","tweet_volume":15441},{"name":"\u8F9E\u8077\u8868\u660E","url":"http:\/\/twitter.com\/search?q=%E8%BE%9E%E8%81%B7%E8%A1%A8%E6%98%8E","promoted_content":null,"query":"%E8%BE%9E%E8%81%B7%E8%A1%A8%E6%98%8E","tweet_volume":null}],"as_of":"2021-11-22T11:45:49Z","created_at":"2021-11-21T00:06:31Z","locations":[{"name":"Worldwide","woeid":1}]}]